universal_image_mcp/__init__.py
universal_image_mcp/providers.py
universal_image_mcp/server.py
universal_image_mcp-0.1.3.dist-info/METADATA
universal_image_mcp-0.1.3.dist-info/WHEEL
universal_image_mcp-0.1.3.dist-info/entry_points.txt
universal_image_mcp-0.1.3.dist-info/licenses/LICENSE
universal_image_mcp-0.1.3.dist-info/RECORD
