Metadata-Version: 2.4
Name: universal-image-mcp
Version: 0.1.3
Summary: Generic MCP server for image generation supporting AWS Bedrock, OpenAI, and Google Gemini
Project-URL: Homepage, https://github.com/manu-mishra/universal-image-mcp
Project-URL: Repository, https://github.com/manu-mishra/universal-image-mcp
Project-URL: Bug Tracker, https://github.com/manu-mishra/universal-image-mcp/issues
Project-URL: LinkedIn, https://www.linkedin.com/in/manu-mishra
Author-email: Manu Mishra <manu.masterman@gmail.com>
License: MIT
License-File: LICENSE
Keywords: aws,gemini,image-generation,llm,mcp,openai
Requires-Python: >=3.11
Requires-Dist: boto3>=1.35.0
Requires-Dist: fastmcp>=2.14.4
Requires-Dist: google-genai>=1.7.0
Requires-Dist: openai>=1.0.0
Requires-Dist: pillow>=12.1.0
Requires-Dist: requests>=2.31.0
Provides-Extra: test
Requires-Dist: pytest-mock>=3.12; extra == 'test'
Requires-Dist: pytest>=8.0; extra == 'test'
